{
  "data": {
    "code": "cu",
    "flag": "https://flagcdn.com/cu.svg",
    "name": {
      "af": "Kuba",
      "am": "ኩባ",
      "ar": "كوبا",
      "az": "Kuba",
      "be": "Куба",
      "bg": "Куба",
      "bn": "কিউবা",
      "bs": "Kuba",
      "ca": "Cuba",
      "cs": "Kuba",
      "cy": "Ciwba",
      "da": "Cuba",
      "de": "Kuba",
      "el": "Κούβα",
      "en": "Cuba",
      "es": "Cuba",
      "et": "Kuuba",
      "eu": "Kuba",
      "fa": "کوبا",
      "fi": "Kuuba",
      "fil": "Cuba",
      "fr": "Cuba",
      "ga": "Cúba",
      "gl": "Cuba",
      "gu": "ક્યુબા",
      "he": "קובה",
      "hi": "क्यूबा",
      "hr": "Kuba",
      "hu": "Kuba",
      "hy": "Կուբա",
      "id": "Kuba",
      "is": "Kúba",
      "it": "Cuba",
      "ja": "キューバ",
      "jv": "Kuba",
      "ka": "კუბა",
      "kk": "Куба",
      "km": "គុយបា",
      "kn": "ಕ್ಯೂಬಾ",
      "ko": "쿠바",
      "ky": "Куба",
      "lo": "ຄິວບາ",
      "lt": "Kuba",
      "lv": "Kuba",
      "mk": "Куба",
      "ml": "ക്യൂബ",
      "mn": "Куба",
      "mr": "क्यूबा",
      "ms": "Cuba",
      "my": "ကျူးဘား",
      "ne": "क्युबा",
      "nl": "Cuba",
      "no": "Cuba",
      "or": "କ‍୍ୟୁବା",
      "pa": "ਕਿਊਬਾ",
      "pl": "Kuba",
      "ps": "کیوبا",
      "pt": "Cuba",
      "ro": "Cuba",
      "ru": "Куба",
      "si": "කියුබාව",
      "sk": "Kuba",
      "sl": "Kuba",
      "sq": "Kubë",
      "sr": "Куба",
      "sv": "Kuba",
      "sw": "Kuba",
      "ta": "கியூபா",
      "te": "క్యూబా",
      "th": "คิวบา",
      "tr": "Küba",
      "uk": "Куба",
      "ur": "کیوبا",
      "uz": "Kuba",
      "vi": "Cuba",
      "zh": "古巴",
      "zu": "i-Cuba",
      "native": {
        "es": "Cuba"
      }
    },
    "lang": {
      "es": {
        "af": "Spaans",
        "am": "ስፓኒሽ",
        "ar": "الإسبانية",
        "az": "ispan",
        "be": "іспанская",
        "bg": "испански",
        "bn": "স্প্যানিশ",
        "bs": "španski",
        "ca": "espanyol",
        "cs": "španělština",
        "cy": "Sbaeneg",
        "da": "spansk",
        "de": "Spanisch",
        "el": "Ισπανικά",
        "en": "Spanish",
        "es": "español",
        "et": "hispaania",
        "eu": "gaztelania",
        "fa": "اسپانیایی",
        "fi": "espanja",
        "fil": "Spanish",
        "fr": "espagnol",
        "ga": "Spáinnis",
        "gl": "español",
        "gu": "સ્પેનિશ",
        "he": "ספרדית",
        "hi": "स्पेनिश",
        "hr": "španjolski",
        "hu": "spanyol",
        "hy": "իսպաներեն",
        "id": "Spanyol",
        "is": "spænska",
        "it": "spagnolo",
        "ja": "スペイン語",
        "jv": "Spanyol",
        "ka": "ესპანური",
        "kk": "испан тілі",
        "km": "អេស្ប៉ាញ",
        "kn": "ಸ್ಪ್ಯಾನಿಷ್",
        "ko": "스페인어",
        "ky": "испанча",
        "lo": "ສະແປນນິຊ",
        "lt": "ispanų",
        "lv": "spāņu",
        "mk": "шпански",
        "ml": "സ്‌പാനിഷ്",
        "mn": "испани",
        "mr": "स्पॅनिश",
        "ms": "Sepanyol",
        "my": "စပိန်",
        "ne": "स्पेनी",
        "nl": "Spaans",
        "no": "spansk",
        "or": "ସ୍ପାନିସ୍‌",
        "pa": "ਸਪੇਨੀ",
        "pl": "hiszpański",
        "ps": "هسپانوي",
        "pt": "espanhol",
        "ro": "spaniolă",
        "ru": "испанский",
        "si": "ස්පාඤ්ඤ",
        "sk": "španielčina",
        "sl": "španščina",
        "sq": "spanjisht",
        "sr": "шпански",
        "sv": "spanska",
        "sw": "Kihispania",
        "ta": "ஸ்பானிஷ்",
        "te": "స్పానిష్",
        "th": "สเปน",
        "tr": "İspanyolca",
        "uk": "іспанська",
        "ur": "ہسپانوی",
        "uz": "ispancha",
        "vi": "Tiếng Tây Ban Nha",
        "zh": "西班牙语",
        "zu": "isi-Spanish",
        "native": {
          "es": "Cuba"
        }
      }
    },
    "phone": "+53"
  },
  "message": "success",
  "status": 200
}