{
  "data": {
    "code": "se",
    "flag": "https://flagcdn.com/se.svg",
    "name": {
      "af": "Swede",
      "am": "ስዊድን",
      "ar": "السويد",
      "az": "İsveç",
      "be": "Швецыя",
      "bg": "Швеция",
      "bn": "সুইডেন",
      "bs": "Švedska",
      "ca": "Suècia",
      "cs": "Švédsko",
      "cy": "Sweden",
      "da": "Sverige",
      "de": "Schweden",
      "el": "Σουηδία",
      "en": "Sweden",
      "es": "Suecia",
      "et": "Rootsi",
      "eu": "Suedia",
      "fa": "سوئد",
      "fi": "Ruotsi",
      "fil": "Sweden",
      "fr": "Suède",
      "ga": "an tSualainn",
      "gl": "Suecia",
      "gu": "સ્વીડન",
      "he": "שוודיה",
      "hi": "स्वीडन",
      "hr": "Švedska",
      "hu": "Svédország",
      "hy": "Շվեդիա",
      "id": "Swedia",
      "is": "Svíþjóð",
      "it": "Svezia",
      "ja": "スウェーデン",
      "jv": "Swèdhen",
      "ka": "შვედეთი",
      "kk": "Швеция",
      "km": "ស៊ុយអែត",
      "kn": "ಸ್ವೀಡನ್",
      "ko": "스웨덴",
      "ky": "Швеция",
      "lo": "ສະວີເດັນ",
      "lt": "Švedija",
      "lv": "Zviedrija",
      "mk": "Шведска",
      "ml": "സ്വീഡൻ",
      "mn": "Швед",
      "mr": "स्वीडन",
      "ms": "Sweden",
      "my": "ဆွီဒင်",
      "ne": "स्विडेन",
      "nl": "Zweden",
      "no": "Sverige",
      "or": "ସ୍ୱିଡେନ୍‌",
      "pa": "ਸਵੀਡਨ",
      "pl": "Szwecja",
      "ps": "سویډن",
      "pt": "Suécia",
      "ro": "Suedia",
      "ru": "Швеция",
      "si": "ස්වීඩනය",
      "sk": "Švédsko",
      "sl": "Švedska",
      "sq": "Suedi",
      "sr": "Шведска",
      "sv": "Sverige",
      "sw": "Uswidi",
      "ta": "ஸ்வீடன்",
      "te": "స్వీడన్",
      "th": "สวีเดน",
      "tr": "İsveç",
      "uk": "Швеція",
      "ur": "سویڈن",
      "uz": "Shvetsiya",
      "vi": "Thụy Điển",
      "zh": "瑞典",
      "zu": "i-Sweden",
      "native": {
        "sv": "Sverige"
      }
    },
    "lang": {
      "sv": {
        "af": "Sweeds",
        "am": "ስዊድንኛ",
        "ar": "السويدية",
        "az": "isveç",
        "be": "шведская",
        "bg": "шведски",
        "bn": "সুইডিশ",
        "bs": "švedski",
        "ca": "suec",
        "cs": "švédština",
        "cy": "Swedeg",
        "da": "svensk",
        "de": "Schwedisch",
        "el": "Σουηδικά",
        "en": "Swedish",
        "es": "sueco",
        "et": "rootsi",
        "eu": "suediera",
        "fa": "سوئدی",
        "fi": "ruotsi",
        "fil": "Swedish",
        "fr": "suédois",
        "ga": "Sualainnis",
        "gl": "sueco",
        "gu": "સ્વીડિશ",
        "he": "שוודית",
        "hi": "स्वीडिश",
        "hr": "švedski",
        "hu": "svéd",
        "hy": "շվեդերեն",
        "id": "Swedia",
        "is": "sænska",
        "it": "svedese",
        "ja": "スウェーデン語",
        "jv": "Swedia",
        "ka": "შვედური",
        "kk": "швед тілі",
        "km": "ស៊ុយអែត",
        "kn": "ಸ್ವೀಡಿಷ್",
        "ko": "스웨덴어",
        "ky": "шведче",
        "lo": "ສະວີດິຊ",
        "lt": "švedų",
        "lv": "zviedru",
        "mk": "шведски",
        "ml": "സ്വീഡിഷ്",
        "mn": "швед",
        "mr": "स्वीडिश",
        "ms": "Sweden",
        "my": "ဆွီဒင်",
        "ne": "स्विडिस",
        "nl": "Zweeds",
        "no": "svensk",
        "or": "ସ୍ୱେଡିସ୍",
        "pa": "ਸਵੀਡਿਸ਼",
        "pl": "szwedzki",
        "ps": "سویډنی",
        "pt": "sueco",
        "ro": "suedeză",
        "ru": "шведский",
        "si": "ස්වීඩන්",
        "sk": "švédčina",
        "sl": "švedščina",
        "sq": "suedisht",
        "sr": "шведски",
        "sv": "svenska",
        "sw": "Kiswidi",
        "ta": "ஸ்வீடிஷ்",
        "te": "స్వీడిష్",
        "th": "สวีเดน",
        "tr": "İsveççe",
        "uk": "шведська",
        "ur": "سویڈش",
        "uz": "shved",
        "vi": "Tiếng Thụy Điển",
        "zh": "瑞典语",
        "zu": "isi-Swedish",
        "native": {
          "sv": "Sverige"
        }
      }
    },
    "phone": "+46"
  },
  "message": "success",
  "status": 200
}