{
  "data": {
    "code": "ve",
    "flag": "https://flagcdn.com/ve.svg",
    "name": {
      "af": "Venezuela",
      "am": "ቬንዙዌላ",
      "ar": "فنزويلا",
      "az": "Venesuela",
      "be": "Венесуэла",
      "bg": "Венецуела",
      "bn": "ভেনেজুয়েলা",
      "bs": "Venecuela",
      "ca": "Veneçuela",
      "cs": "Venezuela",
      "cy": "Venezuela",
      "da": "Venezuela",
      "de": "Venezuela",
      "el": "Βενεζουέλα",
      "en": "Venezuela",
      "es": "Venezuela",
      "et": "Venezuela",
      "eu": "Venezuela",
      "fa": "ونزوئلا",
      "fi": "Venezuela",
      "fil": "Venezuela",
      "fr": "Venezuela",
      "ga": "Veiniséala",
      "gl": "Venezuela",
      "gu": "વેનેઝુએલા",
      "he": "ונצואלה",
      "hi": "वेनेज़ुएला",
      "hr": "Venezuela",
      "hu": "Venezuela",
      "hy": "Վենեսուելա",
      "id": "Venezuela",
      "is": "Venesúela",
      "it": "Venezuela",
      "ja": "ベネズエラ",
      "jv": "Vénésuéla",
      "ka": "ვენესუელა",
      "kk": "Венесуэла",
      "km": "វ៉េណេស៊ុយអេឡា",
      "kn": "ವೆನೆಜುವೆಲಾ",
      "ko": "베네수엘라",
      "ky": "Венесуэла",
      "lo": "ເວເນຊູເອລາ",
      "lt": "Venesuela",
      "lv": "Venecuēla",
      "mk": "Венецуела",
      "ml": "വെനിസ്വേല",
      "mn": "Венесуэл",
      "mr": "व्हेनेझुएला",
      "ms": "Venezuela",
      "my": "ဗင်နီဇွဲလား",
      "ne": "भेनेजुएला",
      "nl": "Venezuela",
      "no": "Venezuela",
      "or": "ଭେନେଜୁଏଲା",
      "pa": "ਵੇਨੇਜ਼ੂਏਲਾ",
      "pl": "Wenezuela",
      "ps": "وینزویلا",
      "pt": "Venezuela",
      "ro": "Venezuela",
      "ru": "Венесуэла",
      "si": "වෙනිසියුලාව",
      "sk": "Venezuela",
      "sl": "Venezuela",
      "sq": "Venezuelë",
      "sr": "Венецуела",
      "sv": "Venezuela",
      "sw": "Venezuela",
      "ta": "வெனிசுலா",
      "te": "వెనిజులా",
      "th": "เวเนซุเอลา",
      "tr": "Venezuela",
      "uk": "Венесуела",
      "ur": "وینزوئیلا",
      "uz": "Venesuela",
      "vi": "Venezuela",
      "zh": "委内瑞拉",
      "zu": "i-Venezuela",
      "native": {
        "es": "Venezuela"
      }
    },
    "lang": {
      "es": {
        "af": "Spaans",
        "am": "ስፓኒሽ",
        "ar": "الإسبانية",
        "az": "ispan",
        "be": "іспанская",
        "bg": "испански",
        "bn": "স্প্যানিশ",
        "bs": "španski",
        "ca": "espanyol",
        "cs": "španělština",
        "cy": "Sbaeneg",
        "da": "spansk",
        "de": "Spanisch",
        "el": "Ισπανικά",
        "en": "Spanish",
        "es": "español",
        "et": "hispaania",
        "eu": "gaztelania",
        "fa": "اسپانیایی",
        "fi": "espanja",
        "fil": "Spanish",
        "fr": "espagnol",
        "ga": "Spáinnis",
        "gl": "español",
        "gu": "સ્પેનિશ",
        "he": "ספרדית",
        "hi": "स्पेनिश",
        "hr": "španjolski",
        "hu": "spanyol",
        "hy": "իսպաներեն",
        "id": "Spanyol",
        "is": "spænska",
        "it": "spagnolo",
        "ja": "スペイン語",
        "jv": "Spanyol",
        "ka": "ესპანური",
        "kk": "испан тілі",
        "km": "អេស្ប៉ាញ",
        "kn": "ಸ್ಪ್ಯಾನಿಷ್",
        "ko": "스페인어",
        "ky": "испанча",
        "lo": "ສະແປນນິຊ",
        "lt": "ispanų",
        "lv": "spāņu",
        "mk": "шпански",
        "ml": "സ്‌പാനിഷ്",
        "mn": "испани",
        "mr": "स्पॅनिश",
        "ms": "Sepanyol",
        "my": "စပိန်",
        "ne": "स्पेनी",
        "nl": "Spaans",
        "no": "spansk",
        "or": "ସ୍ପାନିସ୍‌",
        "pa": "ਸਪੇਨੀ",
        "pl": "hiszpański",
        "ps": "هسپانوي",
        "pt": "espanhol",
        "ro": "spaniolă",
        "ru": "испанский",
        "si": "ස්පාඤ්ඤ",
        "sk": "španielčina",
        "sl": "španščina",
        "sq": "spanjisht",
        "sr": "шпански",
        "sv": "spanska",
        "sw": "Kihispania",
        "ta": "ஸ்பானிஷ்",
        "te": "స్పానిష్",
        "th": "สเปน",
        "tr": "İspanyolca",
        "uk": "іспанська",
        "ur": "ہسپانوی",
        "uz": "ispancha",
        "vi": "Tiếng Tây Ban Nha",
        "zh": "西班牙语",
        "zu": "isi-Spanish",
        "native": {
          "es": "Venezuela"
        }
      }
    },
    "phone": "+58"
  },
  "message": "success",
  "status": 200
}